{
  "Front-windscreen-damage_minor": 1000,
  "Front-windscreen-damage_moderate": 8000,
  "Front-windscreen-damage_severe": 17000,
  "Headlight-damage_minor": 700,
  "Headlight-damage_moderate": 4200,
  "Headlight-damage_severe": 12200,
  "Rear-windscreen-Damage_minor": 800,
  "Rear-windscreen-Damage_moderate": 7000,
  "Rear-windscreen-Damage_severe": 15000,
  "Runningboard-Damage_minor": 1300,
  "Runningboard-Damage_moderate": 4800,
  "Runningboard-Damage_severe": 10700,
  "Sidemirror-Damage_minor": 0,
  "Sidemirror-Damage_moderate": 1800,
  "Sidemirror-Damage_severe": 5100,
  "Taillight-Damage_minor": 0,
  "Taillight-Damage_moderate": 2000,
  "Taillight-Damage_severe": 5600,
  "bonnet-dent_minor": 1400,
  "bonnet-dent_moderate": 5000,
  "bonnet-dent_severe": 11600,
  "boot-dent_minor": 1400,
  "boot-dent_moderate": 5000,
  "boot-dent_severe": 10900,
  "doorouter-dent_minor": 1800,
  "doorouter-dent_moderate": 5600,
  "doorouter-dent_severe": 12300,
  "fender-dent_minor": 1400,
  "fender-dent_moderate": 4200,
  "fender-dent_severe": 9500,
  "front-bumper-dent_minor": 900,
  "front-bumper-dent_moderate": 3700,
  "front-bumper-dent_severe": 8400,
  "quaterpanel-dent_minor": 2200,
  "quaterpanel-dent_moderate": 6700,
  "quaterpanel-dent_severe": 15100,
  "rear-bumper-dent_minor": 900,
  "rear-bumper-dent_moderate": 3400,
  "rear-bumper-dent_severe": 7800,
  "roof-dent_minor": 2500,
  "roof-dent_moderate": 7800,
  "roof-dent_severe": 17200
}
